motion/__init__.py
motion/cli.py
motion/component.py
motion/copy_utils.py
motion/dashboard.py
motion/dashboard_utils.py
motion/df.py
motion/dicts.py
motion/discard_policy.py
motion/execute.py
motion/instance.py
motion/migrate.py
motion/mtable.py
motion/res/eff_short_wordlist_1.txt
motion/route.py
motion/server/__init__.py
motion/server/application.py
motion/server/update_task.py
motion/static/asset-manifest.json
motion/static/index.html
motion/static/logo.png
motion/static/manifest.json
motion/static/robots.txt
motion/static/static/css/main.509f574d.css
motion/static/static/css/main.509f574d.css.map
motion/static/static/js/488.a906bbde.chunk.js
motion/static/static/js/488.a906bbde.chunk.js.map
motion/static/static/js/main.13f04124.js
motion/static/static/js/main.13f04124.js.LICENSE.txt
motion/static/static/js/main.13f04124.js.map
motion/utils.py
motion_python-0.1.132.dist-info/METADATA
motion_python-0.1.132.dist-info/WHEEL
motion_python-0.1.132.dist-info/entry_points.txt
motion_python-0.1.132.dist-info/RECORD
