Metadata-Version: 2.1
Name: motion-python
Version: 0.1.132
Summary: A framework for building and maintaining self-updating prompts for LLMs.
Author: Shreya Shankar
Author-email: shreyashankar@berkeley.edu
Requires-Python: >=3.9,<4.0
Classifier: Programming Language :: Python :: 3
Classifier: Programming Language :: Python :: 3.9
Classifier: Programming Language :: Python :: 3.10
Classifier: Programming Language :: Python :: 3.11
Classifier: Programming Language :: Python :: 3.12
Provides-Extra: all
Provides-Extra: application
Provides-Extra: table
Requires-Dist: click (>=8.1.3,<9.0.0)
Requires-Dist: cloudpickle (>=2.0,<3.0)
Requires-Dist: colorlog (>=6.7.0,<7.0.0)
Requires-Dist: fastapi (>=0.108.0,<0.109.0) ; extra == "application" or extra == "all"
Requires-Dist: fastvs (>=0.1.7,<0.2.0) ; extra == "table" or extra == "all"
Requires-Dist: pandas (>=2.1.0,<3.0.0) ; extra == "table" or extra == "all"
Requires-Dist: psutil (>=5.9.5,<6.0.0)
Requires-Dist: pyarrow (>=14.0.1,<15.0.0) ; extra == "table" or extra == "all"
Requires-Dist: pydantic (>=2.5.3,<3.0.0)
Requires-Dist: pyjwt (>=2.8.0,<3.0.0) ; extra == "application" or extra == "all"
Requires-Dist: pyyaml (>=6.0.1,<7.0.0)
Requires-Dist: redis (>=4.5.5,<5.0.0)
Requires-Dist: rich (>=13.4.1,<14.0.0)
Requires-Dist: tqdm (>=4.66.1,<5.0.0)
